sd5gsim/__init__.py
sd5gsim/clear.png
sd5gsim/exit.png
sd5gsim/gen.png
sd5gsim/icon1.png
sd5gsim/icon2.png
sd5gsim/icon3.png
sd5gsim/icon4.png
sd5gsim/icon5.png
sd5gsim/run.png
sd5gsim-0.2.dist-info/DESCRIPTION.rst
sd5gsim-0.2.dist-info/METADATA
sd5gsim-0.2.dist-info/RECORD
sd5gsim-0.2.dist-info/WHEEL
sd5gsim-0.2.dist-info/metadata.json
sd5gsim-0.2.dist-info/top_level.txt
